{
	"id": "e116e8f6-a515-4d0c-b158-48581bd57299",
	"name": "Local",
	"values": [
		{
			"key": "base_url",
			"value": "http://localhost",
			"enabled": true
		},
		{
			"key": "config-server-port",
			"value": "8088",
			"enabled": true
		},
		{
			"key": "channel-improvement-wizard-v1-port",
			"value": "8080",
			"enabled": true
		},
		{
			"key": "business-customer-v1-port",
			"value": "8071",
			"enabled": true
		},
		{
			"key": "data-customer-v1-port",
			"value": "8072",
			"enabled": true
		},
		{
			"key": "business-product-v1-port",
			"value": "8081",
			"enabled": true
		},
		{
			"key": "data-product-v1-port",
			"value": "8082",
			"enabled": true
		},
		{
			"key": "business-improvement-v1-port",
			"value": "8091",
			"enabled": true
		},
		{
			"key": "data-improvement-v1-port",
			"value": "8092",
			"enabled": true
		}
	],
	"_postman_variable_scope": "environment",
	"_postman_exported_at": "2021-02-09T04:37:26.891Z",
	"_postman_exported_using": "Postman/8.0.4"
}